POKE_DONPOLLO/__init__.py
POKE_DONPOLLO/pokemon.csv
POKE_DONPOLLO/ramdom_pokemon.py
POKE_DONPOLLO-2.0.5.dist-info/METADATA
POKE_DONPOLLO-2.0.5.dist-info/WHEEL
POKE_DONPOLLO-2.0.5.dist-info/top_level.txt
POKE_DONPOLLO-2.0.5.dist-info/RECORD
